{
  "algorithm_info": {
    "id": "QAlgo-Dream-G39",
    "name": "Codegen Mutation G39 [lea_optimization]",
    "domain": "compiler_optimization",
    "discovered_by": "ZCC Oneirogenesis v2 Island-1",
    "lineage_hash": "6209b3ab870ab7d3",
    "island_id": 1
  },
  "mutations": [
    {
      "name": "lea_optimization",
      "category": "IDIOM",
      "description": "Fuse mov+add \u2192 leaq $8(%r15), %rax",
      "is_sweep": false,
      "sweep_count": 0,
      "energy_delta": -3.0,
      "fingerprint": ""
    }
  ],
  "fitness_improvement": {
    "asm_size_delta": -15,
    "inst_count_delta": 118053,
    "score_delta": -8.634895000141114,
    "composite_score": 1252937.600301
  },
  "timestamp": "2026-04-20T11:18:00.174162+00:00",
  "generation": 39
}