{
  "algorithm_info": {
    "id": "QAlgo-Dream-G123",
    "name": "Codegen Mutation G123 [dead_move_elim]",
    "domain": "compiler_optimization",
    "discovered_by": "ZCC Oneirogenesis v2 Island-2",
    "lineage_hash": "f43ec3b5c3eec355",
    "island_id": 2
  },
  "mutations": [
    {
      "name": "dead_move_elim",
      "category": "PEEPHOLE",
      "description": "Remove dead movq to %rax (overwritten at +1)",
      "is_sweep": false,
      "sweep_count": 0,
      "energy_delta": -2.0,
      "fingerprint": ""
    }
  ],
  "fitness_improvement": {
    "asm_size_delta": -20,
    "inst_count_delta": 117817,
    "score_delta": -9.96595500013791,
    "composite_score": 1257378.4061839997
  },
  "timestamp": "2026-04-20T13:45:38.569226+00:00",
  "generation": 123
}